{
  "itemId": "955173449880",
  "url": "https://www.goofish.com/item?id=955173449880&categoryId=126888001",
  "name": "حذاء نسائي بكعب مسطح من Nude، جلد صناعي، لون بيج",
  "originalTitle": "35至40码裸色漆皮尖头平底单鞋女2025新款四季百搭浅口鞋 炸街必备潮鞋  实物拍摄   全新漆皮面料  内增高设计 ［全新捡漏］ 喜欢直接拍  能拍就有 全国包邮  描述清楚售出不退不换",
  "priceCny": 36,
  "newOrOld": null,
  "description": "حذاء نسائي أنيق برقبة منخفضة ورأس مدبب، مصنوع من جلد صناعي لامع عالي الجودة، بتصميم عصري يناسب جميع الفصول. يتوفر بالألوان البيج (العاري) والأحجام من 35 إلى 40، مناسب للارتداء اليومي والمناسبات، ويتميز بتصميم عملي وسهل التنسيق مع مختلف الإطلالات. يتميز الحذاء بتصميم داخلي يمنحك ارتفاعًا إضافيًا بشكل مخفي، مما يعزز القوام دون التضحية بالراحة. السطح الخارجي مصنوع من خامة漆皮 (جلد مصقول) جديدة تمامًا، لامعة وسهلة التنظيف، مع لمسة نهائية أنيقة تمنحك إطلالة جذابة. المنتج جديد بالكامل، لم يُستخدم من قبل، ويُباع كما هو موضح في الصور الحقيقية المرفقة. يُرجى ملاحظة أن الحذاء لا يُستبدل ولا يُسترجع بعد الشراء. الشحن متاح لجميع أنحاء الدولة مجانًا. مثالي للإطلالات اليومية أو الخروجات العصرية، ويُعد خيارًا مثاليًا لكل من ت",
  "specs": null,
  "images": [],
  "imageEmbeddings": [],
  "categoryId": "126888001",
  "soldCount": null,
  "isActive": true,
  "scrapedAt": "2026-05-11T06:19:51.518Z"
}