{
  "itemId": "1022942285683",
  "url": "https://www.goofish.com/item?id=1022942285683&categoryId=126860512",
  "name": "فستان نوم حريري أبيض من Pureyu",
  "originalTitle": null,
  "priceCny": 16.8,
  "newOrOld": true,
  "description": "فستان نوم أنيق على شكل قفطان بأسلوب أنثوي جذاب، لون أبيض واحد بحجم عالمي يناسب الوزن من 40 إلى 65 كجم (80-130 جين). مصنوع من خامة عالية الجودة بتصميم أنيس وراقي، بتصميم دقيق وتفاصيل راقية تضيف لمسة من الجمال والجاذبية. مناسب كفستان نوم أو جزء من طقم ليلة رومانسية لإضفاء لمحة من الحماسة في العلاقة العاطفية. المنتج جديد ولم يُستخدم، ويُباع بسعر مخفض جدًا بسبب إغلاق المتجر نظرًا لانتهاء إيجار المحل. السعر الأصلي 58 يوان، والآن بسعر 16.8 يوان فقط مع شحن مجاني إلى جميع أنحاء البلاد، وتُرسل الطرد بسرية تامة دون أي إشارات على المحتوى. ملاحظة مهمة: نظرًا لطبيعة المنتج كقطعة لباس داخلي، لا يُقبل استبداله أو استرجاعه لضمان سلامة المشتري. المنتج من مخزونات المصنع مباشرة، بدون أي وسطاء، ما يضمن جودة عالية و",
  "specs": {
    "الحالة": "جديد تمامًا",
    "المقاس": "مقاس واحد",
    "عدد المبيعات": "561"
  },
  "images": [
    "https://img.alicdn.com/bao/uploaded/i4/2215182979752/O1CN01qFj7kb2LuTYb0dreL_!!4611686018427384488-0-xy_item.jpg",
    "https://img.alicdn.com/bao/uploaded/i4/2215182979752/O1CN01qFj7kb2LuTYb0dreL_!!4611686018427384488-0-xy_item.jpg_Q90.jpg_",
    "https://img.alicdn.com/bao/uploaded/i4/2215182979752/O1CN01qFj7kb2LuTYb0dreL_!!4611686018427384488-0-xy_item.jpg"
  ],
  "categoryId": "126860512",
  "soldCount": 561,
  "isActive": true,
  "scrapedAt": "2026-05-09T12:33:00.708Z"
}