{
  "itemId": "1048839166794",
  "url": "https://www.goofish.com/item?id=1048839166794&categoryId=126858789",
  "name": "رداء نوم قطني نسائي بتصميم فضفاض - Lazy Version",
  "originalTitle": null,
  "priceCny": 12.9,
  "newOrOld": true,
  "description": "قطعة ناعمة وعملية بتصميم فضفاض ومريح، مناسبة للصيف! هذا المعطف النسائي قصير الأكمام (سبعة أثمان) مصنوع من مادة مشابهة للقطن، ناعمة جدًا وخفيفة، تمنحك شعورًا بالراحة طوال اليوم. التصميم الفضفاض يناسب المقاسات من M إلى XXL، ويناسب من تزن أقل من 70 كجم (140 جين). يمكن ارتداؤه كمعطف نوم أو كمعطف استحمام بعد الاستحمام، كما يناسب ارتداءه فوق فستان حمالات في فصل الصيف. جودة الخياطة ممتازة، بمواصفات طراز الطلب التجاري، وذو سعر اقتصادي جدًا – بأقل من سعر شورت واحد! كمية محدودة من القطع المتبقية من الطلبات السابقة، تُباع بسعر التصفية دون احتساب التكلفة، ولا يُقبل التفاوض على السعر. يرجى كتابة المقاس المطلوب عند الطلب.",
  "specs": {
    "الحالة": "جديد تمامًا",
    "المقاس": "XL",
    "عدد المبيعات": "605"
  },
  "images": [
    "https://img.alicdn.com/bao/uploaded/i2/2206839088706/O1CN01aJhrKk2EBPHsYjEVZ_!!4611686018427381314-53-xy_item.heic",
    "https://img.alicdn.com/bao/uploaded/i3/2206839088706/O1CN01N6koiY2EBPHsxguqu_!!4611686018427381314-53-xy_item.heic",
    "https://img.alicdn.com/bao/uploaded/i4/O1CN015jwzPN2EBPHt4WjEw~livephoto~_!!4611686018427381314-53-fleamarket.heic",
    "https://img.alicdn.com/bao/uploaded/i1/O1CN01wGWLmx2EBPHsrYhlL~livephoto~_!!4611686018427381314-53-fleamarket.heic",
    "https://img.alicdn.com/bao/uploaded/i3/O1CN01tKbdnq2EBPHsYgHZ3~livephoto~_!!4611686018427381314-53-fleamarket.heic",
    "https://img.alicdn.com/bao/uploaded/i4/O1CN01RVu52I2EBPHt92ZhS~livephoto~_!!4611686018427381314-53-fleamarket.heic",
    "https://img.alicdn.com/bao/uploaded/i2/O1CN01cegb5O2EBPHseoCYx~livephoto~_!!4611686018427381314-53-fleamarket.heic",
    "https://img.alicdn.com/bao/uploaded/i2/2206839088706/O1CN01aJhrKk2EBPHsYjEVZ_!!4611686018427381314-53-xy_item.heic_Q90.jpg_",
    "https://img.alicdn.com/bao/uploaded/i3/2206839088706/O1CN01N6koiY2EBPHsxguqu_!!4611686018427381314-53-xy_item.heic_Q90.jpg_",
    "https://img.alicdn.com/bao/uploaded/i4/O1CN015jwzPN2EBPHt4WjEw~livephoto~_!!4611686018427381314-53-fleamarket.heic_Q90.jpg_"
  ],
  "categoryId": "126858789",
  "soldCount": 605,
  "isActive": true,
  "scrapedAt": "2026-05-09T12:41:18.938Z"
}