{
  "itemId": "1013355636348",
  "url": "https://www.goofish.com/item?id=1013355636348&categoryId=126888001",
  "name": "حذاء نسائي أسود من قماش حرير بريميجي",
  "originalTitle": "全新34码黑色绸缎面粗跟中空防水台超高跟女单鞋 跟高13厘米，防水台3厘米！ 25元包邮直接拍！ 图片实拍，不讲价不退不换！",
  "priceCny": 13,
  "newOrOld": null,
  "description": "حذاء نسائي أنيق جديد بالكامل بمقاس 34، بلون أسود أنيق ومصنوع من قماش الساتان اللامع. يتميز الحذاء بكعب سميك عالي جدًا بارتفاع 13 سنتيمترًا، مع منصة مائية (مقاوم للماء) بارتفاع 3 سنتيمترات، مما يمنحه مظهرًا جذابًا ومتانة عالية. التصميم يحتوي على تفاصيل مثقوبة (منقوشة) تضيف لمسة عصرية وجريئة. الحذاء مناسب للارتداء في المناسبات أو لإطلالة يومية مميزة، ويوفر دعمًا جيدًا بفضل كعبه المتين. تم تصوير الحذاء فعليًا في الصور المعروضة، ويُباع كما هو موضح دون إمكانية التفاوض أو الاستبدال أو الاسترجاع. المقاس: 34 اللون: أسود المادة: ساتان ارتفاع الكعب: 13 سم ارتفاع المنصة (المقاومة للماء): 3 سم الحالة: جديد تمامًا",
  "specs": null,
  "images": [],
  "imageEmbeddings": [],
  "categoryId": "126888001",
  "soldCount": null,
  "isActive": true,
  "scrapedAt": "2026-05-11T05:49:16.240Z"
}