{
  "itemId": "1046077382186",
  "url": "https://www.goofish.com/item?id=1046077382186&categoryId=126888001",
  "name": "حذاء عالي بكعب دافني",
  "originalTitle": "全新38码达芙妮浅口水钻高跟鞋女款2026新款夏季玛丽珍单鞋 配裙子绝美婚鞋跟高9厘米包邮，新疆西藏不包邮",
  "priceCny": 65,
  "newOrOld": null,
  "description": "حذاء كعب عالي نسائي أصلي من دافني، موديل جديد صيف 2026، مقاس 38، بتصميم أنيق على شكل ماري جين. يتميز الحذاء بعنق قصير فاتح مع تزيينات من أحجار الراين اللامعة التي تضيف لمسة جذابة ورقيقة. يبلغ ارتفاع الكعب 9 سنتيمترات، مما يمنحك طولاً إضافياً ويشكل خياراً مثالياً للإطلالات الرسمية أو كحذاء زفاف ساحر. مصنوع من مواد عالية الجودة تضمن الراحة أثناء السير، ومثالي للارتداء مع التنانير أو الفساتين للحصول على إطلالة أنيقة وساحرة. الحالة: جديد بالكامل. اللون: بيج فاتح (浅口). ملاحظة: الشحن مجاني لمعظم المناطق، باستثناء منطقتي شينجيانغ والتبت.",
  "specs": null,
  "images": [],
  "imageEmbeddings": [],
  "categoryId": "126888001",
  "soldCount": null,
  "isActive": true,
  "scrapedAt": "2026-05-11T06:05:05.589Z"
}