{
  "itemId": "770706834674",
  "url": "https://www.goofish.com/item?id=770706834674&categoryId=126888001",
  "name": "حذاء نسائي عالي بكعب مربع من Gaudi لون بشرة",
  "originalTitle": "高蒂方扣女鞋秋季新款裸色单鞋女细跟通勤鞋子法式少女高跟鞋 尺码37  喜欢的姐妹联系我拍实物图，紧穿一次几个小时吧，实物九九新",
  "priceCny": 245,
  "newOrOld": null,
  "description": "حذاء نسائي عالي من موديل غاوتي، موديل جديد لخريف، لون بيج كلاسيكي، بتصميم أنيق بكعب عالٍ ودقيق، مناسب للارتداء اليومي في العمل أو المناسبات. يتميز بتفاصيل فرنسية أنثوية تضيف لمسة شبابية وأنيقة. الحذاء بمقاس 37، وتم ارتداؤه مرة واحدة فقط لبضع ساعات، وحالته ممتازة جدًا (تُشبه الجديدة تمامًا). مثالي للسيدات اللواتي يبحثن عن حذاء أنيق وناعم على القدمين. للحصول على صور فعلية للمنتج، يُرجى التواصل مباشرة.",
  "specs": null,
  "images": [],
  "imageEmbeddings": [],
  "categoryId": "126888001",
  "soldCount": null,
  "isActive": true,
  "scrapedAt": "2026-05-11T06:00:42.369Z"
}